calculation1/__init__.py
calculation1/button_names.py
calculation1/calculator.py
calculation1/calculator_date.py
calculation1/calculator_date_page.py
calculation1/calculator_page.py
calculation1/calculator_standard_science.py
calculation1/programmer_page.py
calculation1/science_page.py
calculation1/standard_page.py
tests/__init__.py
calculation1-2.1.0.dist-info/LICENSE
calculation1-2.1.0.dist-info/METADATA
calculation1-2.1.0.dist-info/WHEEL
calculation1-2.1.0.dist-info/top_level.txt
calculation1-2.1.0.dist-info/RECORD
